datallm/__init__.py
datallm/_base_client.py
datallm/_client.py
datallm/_exceptions.py
datallm/_pd_utils.py
datallm/_resources.py
datallm/_types.py
datallm-0.2.6.dist-info/METADATA
datallm-0.2.6.dist-info/WHEEL
datallm-0.2.6.dist-info/RECORD
