Metadata-Version: 2.1
Name: datallm
Version: 0.2.6
Summary: Python client for DataLLM server
License: Apache-2.0
Author: MOSTLY AI
Author-email: office@mostly.ai
Requires-Python: >=3.9,<4.0
Classifier: License :: OSI Approved :: Apache Software License
Classifier: Programming Language :: Python :: 3
Classifier: Programming Language :: Python :: 3.9
Classifier: Programming Language :: Python :: 3.10
Classifier: Programming Language :: Python :: 3.11
Classifier: Programming Language :: Python :: 3.12
Requires-Dist: httpx (>=0.25.1)
Requires-Dist: pandas (>=1.5.3,<3.0.0)
Requires-Dist: pyarrow (>=14.0.2)
Requires-Dist: pydantic (>=2.4.2,<3.0.0)
Requires-Dist: rich (>=13.7.0,<14.0.0)
Requires-Dist: tenacity (>=8.2.3,<9.0.0)
